{
    "gmd_bus": {
        "56": {
            "volt_mag": null,
            "gic_blocker": null
        },
        "35": {
            "volt_mag": null,
            "gic_blocker": null
        },
        "60": {
            "volt_mag": null,
            "gic_blocker": null
        },
        "220": {
            "volt_mag": null,
            "gic_blocker": null
        },
        "67": {
            "volt_mag": null,
            "gic_blocker": null
        },
        "215": {
            "volt_mag": null,
            "gic_blocker": null
        },
        "73": {
            "volt_mag": null,
            "gic_blocker": null
        },
        "115": {
            "volt_mag": null,
            "gic_blocker": null
        },
        "112": {
            "volt_mag": null,
            "gic_blocker": null
        },
        "185": {
            "volt_mag": null,
            "gic_blocker": null
        },
        "86": {
            "volt_mag": null,
            "gic_blocker": null
        },
        "168": {
            "volt_mag": null,
            "gic_blocker": null
        },
        "207": {
            "volt_mag": null,
            "gic_blocker": null
        },
        "242": {
            "volt_mag": null,
            "gic_blocker": null
        },
        "183": {
            "volt_mag": null,
            "gic_blocker": null
        },
        "224": {
            "volt_mag": null,
            "gic_blocker": null
        },
        "177": {
            "volt_mag": null,
            "gic_blocker": null
        },
        "12": {
            "volt_mag": null,
            "gic_blocker": null
        },
        "75": {
            "volt_mag": null,
            "gic_blocker": null
        },
        "23": {
            "volt_mag": null,
            "gic_blocker": null
        },
        "111": {
            "volt_mag": null,
            "gic_blocker": null
        },
        "41": {
            "volt_mag": null,
            "gic_blocker": null
        },
        "68": {
            "volt_mag": null,
            "gic_blocker": null
        },
        "82": {
            "volt_mag": null,
            "gic_blocker": null
        },
        "130": {
            "volt_mag": null,
            "gic_blocker": null
        },
        "125": {
            "volt_mag": null,
            "gic_blocker": null
        },
        "77": {
            "volt_mag": null,
            "gic_blocker": null
        },
        "172": {
            "volt_mag": null,
            "gic_blocker": null
        },
        "71": {
            "volt_mag": null,
            "gic_blocker": null
        },
        "66": {
            "volt_mag": null,
            "gic_blocker": null
        },
        "103": {
            "volt_mag": null,
            "gic_blocker": null
        },
        "59": {
            "volt_mag": null,
            "gic_blocker": null
        },
        "208": {
            "volt_mag": null,
            "gic_blocker": null
        },
        "26": {
            "volt_mag": null,
            "gic_blocker": null
        },
        "211": {
            "volt_mag": null,
            "gic_blocker": null
        },
        "127": {
            "volt_mag": null,
            "gic_blocker": null
        },
        "116": {
            "volt_mag": null,
            "gic_blocker": null
        },
        "100": {
            "volt_mag": null,
            "gic_blocker": null
        },
        "79": {
            "volt_mag": null,
            "gic_blocker": null
        },
        "230": {
            "volt_mag": null,
            "gic_blocker": null
        },
        "195": {
            "volt_mag": null,
            "gic_blocker": null
        },
        "141": {
            "volt_mag": null,
            "gic_blocker": null
        },
        "135": {
            "volt_mag": null,
            "gic_blocker": null
        },
        "138": {
            "volt_mag": null,
            "gic_blocker": null
        },
        "222": {
            "volt_mag": null,
            "gic_blocker": null
        },
        "107": {
            "volt_mag": null,
            "gic_blocker": null
        },
        "46": {
            "volt_mag": null,
            "gic_blocker": null
        },
        "57": {
            "volt_mag": null,
            "gic_blocker": null
        },
        "152": {
            "volt_mag": null,
            "gic_blocker": null
        },
        "247": {
            "volt_mag": null,
            "gic_blocker": null
        },
        "170": {
            "volt_mag": null,
            "gic_blocker": null
        },
        "129": {
            "volt_mag": null,
            "gic_blocker": null
        },
        "238": {
            "volt_mag": null,
            "gic_blocker": null
        },
        "78": {
            "volt_mag": null,
            "gic_blocker": null
        },
        "133": {
            "volt_mag": null,
            "gic_blocker": null
        },
        "72": {
            "volt_mag": null,
            "gic_blocker": null
        },
        "184": {
            "volt_mag": null,
            "gic_blocker": null
        },
        "1": {
            "volt_mag": null,
            "gic_blocker": null
        },
        "137": {
            "volt_mag": null,
            "gic_blocker": null
        },
        "22": {
            "volt_mag": null,
            "gic_blocker": null
        },
        "154": {
            "volt_mag": null,
            "gic_blocker": null
        },
        "237": {
            "volt_mag": null,
            "gic_blocker": null
        },
        "206": {
            "volt_mag": null,
            "gic_blocker": null
        },
        "33": {
            "volt_mag": null,
            "gic_blocker": null
        },
        "40": {
            "volt_mag": null,
            "gic_blocker": null
        },
        "113": {
            "volt_mag": null,
            "gic_blocker": null
        },
        "231": {
            "volt_mag": null,
            "gic_blocker": null
        },
        "245": {
            "volt_mag": null,
            "gic_blocker": null
        },
        "165": {
            "volt_mag": null,
            "gic_blocker": null
        },
        "142": {
            "volt_mag": null,
            "gic_blocker": null
        },
        "5": {
            "volt_mag": null,
            "gic_blocker": null
        },
        "55": {
            "volt_mag": null,
            "gic_blocker": null
        },
        "114": {
            "volt_mag": null,
            "gic_blocker": null
        },
        "136": {
            "volt_mag": null,
            "gic_blocker": null
        },
        "117": {
            "volt_mag": null,
            "gic_blocker": null
        },
        "45": {
            "volt_mag": null,
            "gic_blocker": null
        },
        "145": {
            "volt_mag": null,
            "gic_blocker": null
        },
        "158": {
            "volt_mag": null,
            "gic_blocker": null
        },
        "218": {
            "volt_mag": null,
            "gic_blocker": null
        },
        "176": {
            "volt_mag": null,
            "gic_blocker": null
        },
        "28": {
            "volt_mag": null,
            "gic_blocker": null
        },
        "148": {
            "volt_mag": null,
            "gic_blocker": null
        },
        "92": {
            "volt_mag": null,
            "gic_blocker": null
        },
        "36": {
            "volt_mag": null,
            "gic_blocker": null
        },
        "118": {
            "volt_mag": null,
            "gic_blocker": null
        },
        "162": {
            "volt_mag": null,
            "gic_blocker": null
        },
        "84": {
            "volt_mag": null,
            "gic_blocker": null
        },
        "7": {
            "volt_mag": null,
            "gic_blocker": null
        },
        "25": {
            "volt_mag": null,
            "gic_blocker": null
        },
        "95": {
            "volt_mag": null,
            "gic_blocker": null
        },
        "203": {
            "volt_mag": null,
            "gic_blocker": null
        },
        "232": {
            "volt_mag": null,
            "gic_blocker": null
        },
        "93": {
            "volt_mag": null,
            "gic_blocker": null
        },
        "18": {
            "volt_mag": null,
            "gic_blocker": null
        },
        "240": {
            "volt_mag": null,
            "gic_blocker": null
        },
        "147": {
            "volt_mag": null,
            "gic_blocker": null
        },
        "157": {
            "volt_mag": null,
            "gic_blocker": null
        },
        "16": {
            "volt_mag": null,
            "gic_blocker": null
        },
        "19": {
            "volt_mag": null,
            "gic_blocker": null
        },
        "44": {
            "volt_mag": null,
            "gic_blocker": null
        },
        "31": {
            "volt_mag": null,
            "gic_blocker": null
        },
        "217": {
            "volt_mag": null,
            "gic_blocker": null
        },
        "146": {
            "volt_mag": null,
            "gic_blocker": null
        },
        "74": {
            "volt_mag": null,
            "gic_blocker": null
        },
        "61": {
            "volt_mag": null,
            "gic_blocker": null
        },
        "29": {
            "volt_mag": null,
            "gic_blocker": null
        },
        "212": {
            "volt_mag": null,
            "gic_blocker": null
        },
        "228": {
            "volt_mag": null,
            "gic_blocker": null
        },
        "159": {
            "volt_mag": null,
            "gic_blocker": null
        },
        "193": {
            "volt_mag": null,
            "gic_blocker": null
        },
        "226": {
            "volt_mag": null,
            "gic_blocker": null
        },
        "101": {
            "volt_mag": null,
            "gic_blocker": null
        },
        "105": {
            "volt_mag": null,
            "gic_blocker": null
        },
        "223": {
            "volt_mag": null,
            "gic_blocker": null
        },
        "17": {
            "volt_mag": null,
            "gic_blocker": null
        },
        "166": {
            "volt_mag": null,
            "gic_blocker": null
        },
        "89": {
            "volt_mag": null,
            "gic_blocker": null
        },
        "198": {
            "volt_mag": null,
            "gic_blocker": null
        },
        "214": {
            "volt_mag": null,
            "gic_blocker": null
        },
        "80": {
            "volt_mag": null,
            "gic_blocker": null
        },
        "51": {
            "volt_mag": null,
            "gic_blocker": null
        },
        "246": {
            "volt_mag": null,
            "gic_blocker": null
        },
        "143": {
            "volt_mag": null,
            "gic_blocker": null
        },
        "48": {
            "volt_mag": null,
            "gic_blocker": null
        },
        "15": {
            "volt_mag": null,
            "gic_blocker": null
        },
        "97": {
            "volt_mag": null,
            "gic_blocker": null
        },
        "134": {
            "volt_mag": null,
            "gic_blocker": null
        },
        "110": {
            "volt_mag": null,
            "gic_blocker": null
        },
        "30": {
            "volt_mag": null,
            "gic_blocker": null
        },
        "6": {
            "volt_mag": null,
            "gic_blocker": null
        },
        "234": {
            "volt_mag": null,
            "gic_blocker": null
        },
        "219": {
            "volt_mag": null,
            "gic_blocker": null
        },
        "182": {
            "volt_mag": null,
            "gic_blocker": null
        },
        "164": {
            "volt_mag": null,
            "gic_blocker": null
        },
        "153": {
            "volt_mag": null,
            "gic_blocker": null
        },
        "186": {
            "volt_mag": null,
            "gic_blocker": null
        },
        "64": {
            "volt_mag": null,
            "gic_blocker": null
        },
        "90": {
            "volt_mag": null,
            "gic_blocker": null
        },
        "139": {
            "volt_mag": null,
            "gic_blocker": null
        },
        "4": {
            "volt_mag": null,
            "gic_blocker": null
        },
        "13": {
            "volt_mag": null,
            "gic_blocker": null
        },
        "104": {
            "volt_mag": null,
            "gic_blocker": null
        },
        "52": {
            "volt_mag": null,
            "gic_blocker": null
        },
        "179": {
            "volt_mag": null,
            "gic_blocker": null
        },
        "43": {
            "volt_mag": null,
            "gic_blocker": null
        },
        "11": {
            "volt_mag": null,
            "gic_blocker": null
        },
        "69": {
            "volt_mag": null,
            "gic_blocker": null
        },
        "171": {
            "volt_mag": null,
            "gic_blocker": null
        },
        "85": {
            "volt_mag": null,
            "gic_blocker": null
        },
        "119": {
            "volt_mag": null,
            "gic_blocker": null
        },
        "39": {
            "volt_mag": null,
            "gic_blocker": null
        },
        "216": {
            "volt_mag": null,
            "gic_blocker": null
        },
        "126": {
            "volt_mag": null,
            "gic_blocker": null
        },
        "108": {
            "volt_mag": null,
            "gic_blocker": null
        },
        "156": {
            "volt_mag": null,
            "gic_blocker": null
        },
        "2": {
            "volt_mag": null,
            "gic_blocker": null
        },
        "10": {
            "volt_mag": null,
            "gic_blocker": null
        },
        "27": {
            "volt_mag": null,
            "gic_blocker": null
        },
        "124": {
            "volt_mag": null,
            "gic_blocker": null
        },
        "144": {
            "volt_mag": null,
            "gic_blocker": null
        },
        "200": {
            "volt_mag": null,
            "gic_blocker": null
        },
        "20": {
            "volt_mag": null,
            "gic_blocker": null
        },
        "81": {
            "volt_mag": null,
            "gic_blocker": null
        },
        "187": {
            "volt_mag": null,
            "gic_blocker": null
        },
        "213": {
            "volt_mag": null,
            "gic_blocker": null
        },
        "9": {
            "volt_mag": null,
            "gic_blocker": null
        },
        "189": {
            "volt_mag": null,
            "gic_blocker": null
        },
        "227": {
            "volt_mag": null,
            "gic_blocker": null
        },
        "109": {
            "volt_mag": null,
            "gic_blocker": null
        },
        "161": {
            "volt_mag": null,
            "gic_blocker": null
        },
        "241": {
            "volt_mag": null,
            "gic_blocker": null
        },
        "88": {
            "volt_mag": null,
            "gic_blocker": null
        },
        "209": {
            "volt_mag": null,
            "gic_blocker": null
        },
        "236": {
            "volt_mag": null,
            "gic_blocker": null
        },
        "120": {
            "volt_mag": null,
            "gic_blocker": null
        },
        "24": {
            "volt_mag": null,
            "gic_blocker": null
        },
        "8": {
            "volt_mag": null,
            "gic_blocker": null
        },
        "37": {
            "volt_mag": null,
            "gic_blocker": null
        },
        "83": {
            "volt_mag": null,
            "gic_blocker": null
        },
        "190": {
            "volt_mag": null,
            "gic_blocker": null
        },
        "201": {
            "volt_mag": null,
            "gic_blocker": null
        },
        "99": {
            "volt_mag": null,
            "gic_blocker": null
        },
        "121": {
            "volt_mag": null,
            "gic_blocker": null
        },
        "14": {
            "volt_mag": null,
            "gic_blocker": null
        },
        "174": {
            "volt_mag": null,
            "gic_blocker": null
        },
        "123": {
            "volt_mag": null,
            "gic_blocker": null
        },
        "32": {
            "volt_mag": null,
            "gic_blocker": null
        },
        "197": {
            "volt_mag": null,
            "gic_blocker": null
        },
        "233": {
            "volt_mag": null,
            "gic_blocker": null
        },
        "196": {
            "volt_mag": null,
            "gic_blocker": null
        },
        "210": {
            "volt_mag": null,
            "gic_blocker": null
        },
        "151": {
            "volt_mag": null,
            "gic_blocker": null
        },
        "239": {
            "volt_mag": null,
            "gic_blocker": null
        },
        "54": {
            "volt_mag": null,
            "gic_blocker": null
        },
        "63": {
            "volt_mag": null,
            "gic_blocker": null
        },
        "191": {
            "volt_mag": null,
            "gic_blocker": null
        },
        "91": {
            "volt_mag": null,
            "gic_blocker": null
        },
        "62": {
            "volt_mag": null,
            "gic_blocker": null
        },
        "205": {
            "volt_mag": null,
            "gic_blocker": null
        },
        "244": {
            "volt_mag": null,
            "gic_blocker": null
        },
        "150": {
            "volt_mag": null,
            "gic_blocker": null
        },
        "122": {
            "volt_mag": null,
            "gic_blocker": null
        },
        "58": {
            "volt_mag": null,
            "gic_blocker": null
        },
        "199": {
            "volt_mag": null,
            "gic_blocker": null
        },
        "173": {
            "volt_mag": null,
            "gic_blocker": null
        },
        "188": {
            "volt_mag": null,
            "gic_blocker": null
        },
        "98": {
            "volt_mag": null,
            "gic_blocker": null
        },
        "235": {
            "volt_mag": null,
            "gic_blocker": null
        },
        "204": {
            "volt_mag": null,
            "gic_blocker": null
        },
        "76": {
            "volt_mag": null,
            "gic_blocker": null
        },
        "34": {
            "volt_mag": null,
            "gic_blocker": null
        },
        "50": {
            "volt_mag": null,
            "gic_blocker": null
        },
        "243": {
            "volt_mag": null,
            "gic_blocker": null
        },
        "194": {
            "volt_mag": null,
            "gic_blocker": null
        },
        "167": {
            "volt_mag": null,
            "gic_blocker": null
        },
        "42": {
            "volt_mag": null,
            "gic_blocker": null
        },
        "87": {
            "volt_mag": null,
            "gic_blocker": null
        },
        "132": {
            "volt_mag": null,
            "gic_blocker": null
        },
        "140": {
            "volt_mag": null,
            "gic_blocker": null
        },
        "202": {
            "volt_mag": null,
            "gic_blocker": null
        },
        "248": {
            "volt_mag": null,
            "gic_blocker": null
        },
        "169": {
            "volt_mag": null,
            "gic_blocker": null
        },
        "180": {
            "volt_mag": null,
            "gic_blocker": null
        },
        "160": {
            "volt_mag": null,
            "gic_blocker": null
        },
        "49": {
            "volt_mag": null,
            "gic_blocker": null
        },
        "106": {
            "volt_mag": null,
            "gic_blocker": null
        },
        "94": {
            "volt_mag": null,
            "gic_blocker": null
        },
        "225": {
            "volt_mag": null,
            "gic_blocker": null
        },
        "102": {
            "volt_mag": null,
            "gic_blocker": null
        },
        "128": {
            "volt_mag": null,
            "gic_blocker": null
        },
        "70": {
            "volt_mag": null,
            "gic_blocker": null
        },
        "21": {
            "volt_mag": null,
            "gic_blocker": null
        },
        "229": {
            "volt_mag": null,
            "gic_blocker": null
        },
        "38": {
            "volt_mag": null,
            "gic_blocker": null
        },
        "163": {
            "volt_mag": null,
            "gic_blocker": null
        },
        "131": {
            "volt_mag": null,
            "gic_blocker": null
        },
        "192": {
            "volt_mag": null,
            "gic_blocker": null
        },
        "221": {
            "volt_mag": null,
            "gic_blocker": null
        },
        "53": {
            "volt_mag": null,
            "gic_blocker": null
        },
        "47": {
            "volt_mag": null,
            "gic_blocker": null
        },
        "175": {
            "volt_mag": null,
            "gic_blocker": null
        },
        "3": {
            "volt_mag": null,
            "gic_blocker": null
        },
        "178": {
            "volt_mag": null,
            "gic_blocker": null
        },
        "96": {
            "volt_mag": null,
            "gic_blocker": null
        },
        "149": {
            "volt_mag": null,
            "gic_blocker": null
        },
        "155": {
            "volt_mag": null,
            "gic_blocker": null
        },
        "181": {
            "volt_mag": null,
            "gic_blocker": null
        },
        "65": {
            "volt_mag": null,
            "gic_blocker": null
        }
    },
    "bus": {
        "5": {
            "qd": 0.456095,
            "pd": 1.9371749999999996
        },
        "56": {
            "qd": 0.45396,
            "pd": 1.9470000000000003
        },
        "35": {
            "qd": 0.56784,
            "pd": 1.3284000000000002
        },
        "55": {
            "qd": 0.25680000000000003,
            "pd": 1.2952449999999998
        },
        "110": {
            "qd": 0.0,
            "pd": 0.0
        },
        "114": {
            "qd": 0.0,
            "pd": 0.0
        },
        "123": {
            "qd": 0.0,
            "pd": 0.0
        },
        "60": {
            "qd": 0.38896,
            "pd": 1.11663
        },
        "30": {
            "qd": 0.46871,
            "pd": 1.569855
        },
        "32": {
            "qd": 0.52514,
            "pd": 1.5076800000000001
        },
        "6": {
            "qd": 0.469455,
            "pd": 1.88268
        },
        "67": {
            "qd": 0.46126500000000004,
            "pd": 1.618575
        },
        "45": {
            "qd": 0.64699,
            "pd": 2.270215
        },
        "117": {
            "qd": 0.0,
            "pd": 0.0
        },
        "136": {
            "qd": 0.0,
            "pd": 0.0
        },
        "145": {
            "qd": 0.0,
            "pd": 0.0
        },
        "73": {
            "qd": 0.22554,
            "pd": 0.7474050000000001
        },
        "115": {
            "qd": 0.0,
            "pd": 0.0
        },
        "112": {
            "qd": 0.0,
            "pd": 0.0
        },
        "64": {
            "qd": 0.49725,
            "pd": 2.32632
        },
        "90": {
            "qd": 0.5386500000000001,
            "pd": 2.088765
        },
        "139": {
            "qd": 0.0,
            "pd": 0.0
        },
        "4": {
            "qd": 0.42455499999999996,
            "pd": 1.7249100000000002
        },
        "13": {
            "qd": 0.42941999999999997,
            "pd": 1.9499700000000004
        },
        "54": {
            "qd": 0.50255,
            "pd": 1.9487999999999999
        },
        "63": {
            "qd": 0.47564999999999996,
            "pd": 1.4835200000000002
        },
        "86": {
            "qd": 0.506065,
            "pd": 1.869
        },
        "104": {
            "qd": 0.0,
            "pd": 0.0
        },
        "91": {
            "qd": 0.16839,
            "pd": 0.5908500000000001
        },
        "62": {
            "qd": 0.44992,
            "pd": 1.3294400000000002
        },
        "150": {
            "qd": 0.0,
            "pd": 0.0
        },
        "122": {
            "qd": 0.0,
            "pd": 0.0
        },
        "58": {
            "qd": 0.1881,
            "pd": 0.627095
        },
        "52": {
            "qd": 0.30719,
            "pd": 1.0779699999999999
        },
        "12": {
            "qd": 0.303535,
            "pd": 1.1903499999999998
        },
        "28": {
            "qd": 0.35501499999999997,
            "pd": 1.3112000000000001
        },
        "75": {
            "qd": 0.439635,
            "pd": 1.6162300000000003
        },
        "23": {
            "qd": 0.560175,
            "pd": 1.77821
        },
        "111": {
            "qd": 0.0,
            "pd": 0.0
        },
        "148": {
            "qd": 0.0,
            "pd": 0.0
        },
        "92": {
            "qd": 0.0,
            "pd": 0.0
        },
        "41": {
            "qd": 0.36760000000000004,
            "pd": 1.2898399999999999
        },
        "43": {
            "qd": 0.5918,
            "pd": 1.8878
        },
        "11": {
            "qd": 0.568365,
            "pd": 2.08923
        },
        "36": {
            "qd": 0.0228,
            "pd": 0.10500000000000001
        },
        "68": {
            "qd": 0.20911000000000005,
            "pd": 0.6002099999999999
        },
        "69": {
            "qd": 0.20295000000000002,
            "pd": 0.6475
        },
        "98": {
            "qd": 0.0,
            "pd": 0.0
        },
        "82": {
            "qd": 0.45654,
            "pd": 1.6781600000000003
        },
        "85": {
            "qd": 0.22187999999999997,
            "pd": 0.681135
        },
        "118": {
            "qd": 0.0,
            "pd": 0.0
        },
        "119": {
            "qd": 0.0,
            "pd": 0.0
        },
        "125": {
            "qd": 0.0,
            "pd": 0.0
        },
        "130": {
            "qd": 0.0,
            "pd": 0.0
        },
        "39": {
            "qd": 0.21406,
            "pd": 0.8194800000000001
        },
        "84": {
            "qd": 0.21065,
            "pd": 0.6718000000000001
        },
        "77": {
            "qd": 0.4208,
            "pd": 1.550115
        },
        "7": {
            "qd": 0.42196000000000006,
            "pd": 1.27851
        },
        "25": {
            "qd": 0.09579499999999999,
            "pd": 0.35586
        },
        "95": {
            "qd": 0.0,
            "pd": 0.0
        },
        "126": {
            "qd": 0.0,
            "pd": 0.0
        },
        "108": {
            "qd": 0.0,
            "pd": 0.0
        },
        "71": {
            "qd": 0.5920949999999999,
            "pd": 1.9785
        },
        "66": {
            "qd": 0.27830000000000005,
            "pd": 0.7102400000000001
        },
        "76": {
            "qd": 0.38432,
            "pd": 1.6012250000000001
        },
        "103": {
            "qd": 0.0,
            "pd": 0.0
        },
        "34": {
            "qd": 0.47281500000000004,
            "pd": 1.3430849999999999
        },
        "50": {
            "qd": 0.374255,
            "pd": 1.23608
        },
        "59": {
            "qd": 0.41556000000000004,
            "pd": 1.2151
        },
        "93": {
            "qd": 0.0,
            "pd": 0.0
        },
        "2": {
            "qd": 0.42024,
            "pd": 1.935255
        },
        "10": {
            "qd": 0.24876,
            "pd": 0.8362799999999999
        },
        "18": {
            "qd": 0.36950000000000005,
            "pd": 1.10211
        },
        "26": {
            "qd": 0.43804499999999996,
            "pd": 1.2941600000000002
        },
        "27": {
            "qd": 0.51066,
            "pd": 1.5927200000000001
        },
        "124": {
            "qd": 0.0,
            "pd": 0.0
        },
        "42": {
            "qd": 0.35552,
            "pd": 1.40346
        },
        "87": {
            "qd": 0.3014,
            "pd": 0.817275
        },
        "127": {
            "qd": 0.0,
            "pd": 0.0
        },
        "116": {
            "qd": 0.0,
            "pd": 0.0
        },
        "100": {
            "qd": 0.0,
            "pd": 0.0
        },
        "132": {
            "qd": 0.0,
            "pd": 0.0
        },
        "140": {
            "qd": 0.0,
            "pd": 0.0
        },
        "79": {
            "qd": 0.57225,
            "pd": 1.6254549999999999
        },
        "16": {
            "qd": 0.39249500000000004,
            "pd": 1.3773549999999999
        },
        "20": {
            "qd": 0.22632,
            "pd": 1.09186
        },
        "81": {
            "qd": 0.490035,
            "pd": 1.8011400000000004
        },
        "144": {
            "qd": 0.0,
            "pd": 0.0
        },
        "147": {
            "qd": 0.0,
            "pd": 0.0
        },
        "141": {
            "qd": 0.0,
            "pd": 0.0
        },
        "19": {
            "qd": 0.4608,
            "pd": 1.77837
        },
        "49": {
            "qd": 0.5685,
            "pd": 1.69541
        },
        "44": {
            "qd": 0.27829000000000004,
            "pd": 1.37832
        },
        "135": {
            "qd": 0.0,
            "pd": 0.0
        },
        "9": {
            "qd": 0.47737499999999994,
            "pd": 1.4104800000000002
        },
        "31": {
            "qd": 0.4384,
            "pd": 1.5382
        },
        "146": {
            "qd": 0.0,
            "pd": 0.0
        },
        "74": {
            "qd": 0.44595,
            "pd": 1.9122400000000002
        },
        "138": {
            "qd": 0.0,
            "pd": 0.0
        },
        "106": {
            "qd": 0.0,
            "pd": 0.0
        },
        "109": {
            "qd": 0.0,
            "pd": 0.0
        },
        "61": {
            "qd": 0.41294000000000003,
            "pd": 1.44903
        },
        "29": {
            "qd": 0.4032,
            "pd": 1.4147999999999998
        },
        "94": {
            "qd": 0.0,
            "pd": 0.0
        },
        "107": {
            "qd": 0.0,
            "pd": 0.0
        },
        "46": {
            "qd": 0.27972,
            "pd": 0.98133
        },
        "57": {
            "qd": 0.29560000000000003,
            "pd": 1.4910899999999998
        },
        "102": {
            "qd": 0.0,
            "pd": 0.0
        },
        "128": {
            "qd": 0.0,
            "pd": 0.0
        },
        "70": {
            "qd": 0.08694,
            "pd": 0.40679999999999994
        },
        "21": {
            "qd": 0.5646300000000001,
            "pd": 1.8009
        },
        "38": {
            "qd": 0.10989000000000002,
            "pd": 0.40698000000000006
        },
        "88": {
            "qd": 0.15920499999999999,
            "pd": 0.7885199999999999
        },
        "129": {
            "qd": 0.0,
            "pd": 0.0
        },
        "131": {
            "qd": 0.0,
            "pd": 0.0
        },
        "120": {
            "qd": 0.0,
            "pd": 0.0
        },
        "101": {
            "qd": 0.0,
            "pd": 0.0
        },
        "78": {
            "qd": 0.4811749999999999,
            "pd": 1.95492
        },
        "105": {
            "qd": 0.0,
            "pd": 0.0
        },
        "133": {
            "qd": 0.0,
            "pd": 0.0
        },
        "72": {
            "qd": 0.40256000000000003,
            "pd": 1.57871
        },
        "24": {
            "qd": 0.18175499999999997,
            "pd": 0.6074
        },
        "8": {
            "qd": 0.6682799999999999,
            "pd": 1.5632000000000001
        },
        "17": {
            "qd": 0.4642,
            "pd": 1.8732349999999995
        },
        "37": {
            "qd": 0.29928,
            "pd": 0.919065
        },
        "1": {
            "qd": 0.0,
            "pd": 0.0
        },
        "53": {
            "qd": 0.5253,
            "pd": 1.47448
        },
        "22": {
            "qd": 0.5279149999999999,
            "pd": 2.14489
        },
        "47": {
            "qd": 0.56936,
            "pd": 1.9067999999999998
        },
        "83": {
            "qd": 0.2856,
            "pd": 0.876855
        },
        "137": {
            "qd": 0.0,
            "pd": 0.0
        },
        "99": {
            "qd": 0.0,
            "pd": 0.0
        },
        "121": {
            "qd": 0.0,
            "pd": 0.0
        },
        "89": {
            "qd": 0.4092,
            "pd": 1.6154100000000002
        },
        "14": {
            "qd": 0.65274,
            "pd": 1.79253
        },
        "3": {
            "qd": 0.4717,
            "pd": 1.32416
        },
        "80": {
            "qd": 0.5261300000000001,
            "pd": 1.9301599999999999
        },
        "96": {
            "qd": 0.0,
            "pd": 0.0
        },
        "51": {
            "qd": 0.40856000000000003,
            "pd": 1.5231999999999999
        },
        "33": {
            "qd": 0.59577,
            "pd": 1.6922650000000001
        },
        "149": {
            "qd": 0.0,
            "pd": 0.0
        },
        "143": {
            "qd": 0.0,
            "pd": 0.0
        },
        "40": {
            "qd": 0.559125,
            "pd": 2.0552400000000004
        },
        "48": {
            "qd": 0.093975,
            "pd": 0.37679999999999997
        },
        "113": {
            "qd": 0.0,
            "pd": 0.0
        },
        "15": {
            "qd": 0.5085000000000001,
            "pd": 1.4275200000000001
        },
        "65": {
            "qd": 0.28764,
            "pd": 1.00929
        },
        "97": {
            "qd": 0.0,
            "pd": 0.0
        },
        "142": {
            "qd": 0.0,
            "pd": 0.0
        },
        "134": {
            "qd": 0.0,
            "pd": 0.0
        }
    }
}
